ShenruJiexiGo/README.md
ShenruJiexiGo/__init__.py
ShenruJiexiGo/__main__.py
ShenruJiexiGo/file.epub
ShenruJiexiGo/index.html
ShenruJiexiGo/css/__init__.py
ShenruJiexiGo/css/annotations.css
ShenruJiexiGo/css/main.css
ShenruJiexiGo/css/normalize.css
ShenruJiexiGo/css/popup.css
ShenruJiexiGo/font/__init__.py
ShenruJiexiGo/font/fontello.eot
ShenruJiexiGo/font/fontello.svg
ShenruJiexiGo/font/fontello.ttf
ShenruJiexiGo/font/fontello.woff
ShenruJiexiGo/img/__init__.py
ShenruJiexiGo/img/annotator-glyph-sprite.png
ShenruJiexiGo/img/annotator-icon-sprite.png
ShenruJiexiGo/img/apple-touch-icon.png
ShenruJiexiGo/img/cancelfullscreen.png
ShenruJiexiGo/img/close.png
ShenruJiexiGo/img/fullscreen.png
ShenruJiexiGo/img/loader.gif
ShenruJiexiGo/img/menu-icon.png
ShenruJiexiGo/img/save.png
ShenruJiexiGo/img/saved.png
ShenruJiexiGo/img/settings-s.png
ShenruJiexiGo/img/settings.png
ShenruJiexiGo/img/star.png
ShenruJiexiGo/js/__init__.py
ShenruJiexiGo/js/epub.js
ShenruJiexiGo/js/epub.min.js
ShenruJiexiGo/js/epub.min.map
ShenruJiexiGo/js/hooks.min.js
ShenruJiexiGo/js/hooks.min.map
ShenruJiexiGo/js/reader.js
ShenruJiexiGo/js/reader.js.map
ShenruJiexiGo/js/reader.min.js
ShenruJiexiGo/js/reader.min.map
ShenruJiexiGo/js/hooks/__init__.py
ShenruJiexiGo/js/hooks/extensions/__init__.py
ShenruJiexiGo/js/hooks/extensions/highlight.js
ShenruJiexiGo/js/libs/__init__.py
ShenruJiexiGo/js/libs/jquery.min.js
ShenruJiexiGo/js/libs/localforage.min.js
ShenruJiexiGo/js/libs/screenfull.js
ShenruJiexiGo/js/libs/screenfull.min.js
ShenruJiexiGo/js/libs/zip.min.js
ShenruJiexiGo/js/plugins/__init__.py
ShenruJiexiGo/js/plugins/hypothesis.js
ShenruJiexiGo/js/plugins/search.js
shenru_jiexi_go-2024.3.1.0.dist-info/METADATA
shenru_jiexi_go-2024.3.1.0.dist-info/WHEEL
shenru_jiexi_go-2024.3.1.0.dist-info/entry_points.txt
shenru_jiexi_go-2024.3.1.0.dist-info/top_level.txt
shenru_jiexi_go-2024.3.1.0.dist-info/RECORD
